{
    "Infinitivo": [
        "pueder"
    ],
    "Gerundio": [
        "puediendo"
    ],
    "Participio": [
        "pudido"
    ],
    "Presente": [
        "puedo",
        "puedes",
        "puede",
        "puedemos",
        "puedesh",
        "pueden"
    ],
    "Pretérito imperfecto  o  Copretérito (Andrés Bello)": [
        "puediya",
        "puediyas",
        "puediya",
        "puediyamos",
        "puediyash",
        "puediyan"
    ],
    "Pretérito indefinido  o  Pretérito (Perfecto simple)": [
        "pude",
        "pudites",
        "pudo",
        "pudimos",
        "puditesh",
        "pudyeron / pudieron"
    ],
    "Futuro": [
        "puedré",
        "puedrás",
        "puedrá",
        "puedremos",
        "puedrásh",
        "puedrán"
    ],
    "Condicional  o  Pospretérito": [
        "puedriya",
        "puedriyas",
        "puedriya",
        "puedriyamos",
        "puedriyash",
        "puedriyan"
    ],
    "Participio presente": [
        "esto puediendo",
        "estas puediendo",
        "esta puediendo",
        "estamos puediendo",
        "estash puediendo",
        "estan puediendo"
    ],
    "Participio pasado": [
        "estava puediendo",
        "estavas puediendo",
        "estava puediendo",
        "estavamos puediendo",
        "estavash puediendo",
        "estavan puediendo"
    ],
    "Pretérito perfecto  o  Antepresente": [
        "tengo pudido",
        "tyenes / tienes pudido",
        "tyene / tiene pudido",
        "tenemos pudido",
        "tenesh pudido",
        "tyenen / tienen pudido"
    ],
    "Pretérito pluscuamperfecto  o  Antecopretérito": [
        "aviya pudido",
        "aviyas pudido",
        "aviya pudido",
        "aviyamos pudido",
        "aviyash pudido",
        "aviyan pudido"
    ],
    "Futuro próximo": [
        "vo / v'a pueder",
        "vas a pueder",
        "va pueder",
        "vamos a pueder",
        "vash a pueder",
        "van a pueder"
    ],
    "Presente_Subjuntivo": [
        "pueda",
        "puedas",
        "pueda",
        "puedamos",
        "puedash",
        "puedan"
    ],
    "Pretérito imperfecto  o  Pretérito": [
        "pudyera / pudiera",
        "pudyeras / pudieras",
        "pudyera / pudiera",
        "pudyéramos / pudiéramos",
        "puedyerash / puedierash",
        "puedyeran / puedieran"
    ],
    "Afirmativo": [
        "puede",
        "pueda",
        "puedamos",
        "pueded",
        "puedan"
    ],
    "Negativo": [
        "Se emplea el presente del modo subjuntivo"
    ]
}